lotion/CHANGELOG.md
lotion/__init__.py
lotion/base_operator.py
lotion/base_page.py
lotion/datetime_utils.py
lotion/file_upload.py
lotion/lotion.py
lotion/property_translator.py
lotion/py.typed
lotion/block/__init__.py
lotion/block/block.py
lotion/block/block_factory.py
lotion/block/block_type.py
lotion/block/bookmark.py
lotion/block/bulleted_list_item.py
lotion/block/callout.py
lotion/block/child_database.py
lotion/block/child_page.py
lotion/block/code.py
lotion/block/column_list.py
lotion/block/divider.py
lotion/block/embed.py
lotion/block/file.py
lotion/block/heading.py
lotion/block/image.py
lotion/block/numbered_list_item.py
lotion/block/paragraph.py
lotion/block/quote.py
lotion/block/table.py
lotion/block/to_do.py
lotion/block/video.py
lotion/block/rich_text/__init__.py
lotion/block/rich_text/rich_text.py
lotion/block/rich_text/rich_text_builder.py
lotion/block/rich_text/rich_text_element.py
lotion/decorator/__init__.py
lotion/decorator/notion_database.py
lotion/decorator/notion_prop.py
lotion/filter/__init__.py
lotion/filter/builder.py
lotion/filter/condition_ruleset.py
lotion/filter/condition/__init__.py
lotion/filter/condition/cond.py
lotion/page/__init__.py
lotion/page/page_id.py
lotion/properties/__init__.py
lotion/properties/button.py
lotion/properties/checkbox.py
lotion/properties/cover.py
lotion/properties/created_by.py
lotion/properties/created_time.py
lotion/properties/date.py
lotion/properties/email.py
lotion/properties/files.py
lotion/properties/formula.py
lotion/properties/icon.py
lotion/properties/last_edited_by.py
lotion/properties/last_edited_time.py
lotion/properties/multi_select.py
lotion/properties/number.py
lotion/properties/parent.py
lotion/properties/person.py
lotion/properties/phone_number.py
lotion/properties/prop.py
lotion/properties/properties.py
lotion/properties/property.py
lotion/properties/relation.py
lotion/properties/rollup.py
lotion/properties/select.py
lotion/properties/status.py
lotion/properties/text.py
lotion-0.9.6.dist-info/METADATA
lotion-0.9.6.dist-info/WHEEL
lotion-0.9.6.dist-info/licenses/LICENSE
lotion-0.9.6.dist-info/RECORD
