Metadata-Version: 2.4
Name: lotion
Version: 0.9.6
Summary: A wrapper of Notion client for Python
Project-URL: Homepage, https://github.com/koboriakira/lotion
Project-URL: Repository, https://github.com/koboriakira/lotion
Project-URL: Issues, https://github.com/koboriakira/lotion/issues
Author-email: Akira Kobori <private.beats@gmail.com>
License: MIT
License-File: LICENSE
Requires-Python: >=3.11
Requires-Dist: notion-client>=2.7.0
Requires-Dist: requests>=2.31.0
